[
  {
    "yield": 0.92,
    "name": "실리콘 웨이퍼 8인치",
    "id": "S001",
    "avgProductionTime": 3,
    "stock": 1
  },
  {
    "yield": 0.88,
    "name": "실리콘 웨이퍼 12인치",
    "id": "S002",
    "avgProductionTime": 3,
    "stock": 3
  },
  {
    "yield": 0.75,
    "name": "GaN 에피택시 웨이퍼",
    "id": "S003",
    "avgProductionTime": 4,
    "stock": 15
  },
  {
    "yield": 0.8,
    "name": "SiC 파워 소자 시료",
    "id": "S004",
    "avgProductionTime": 3,
    "stock": 20
  },
  {
    "yield": 0.95,
    "name": "MEMS 압력센서 시료",
    "id": "S005",
    "avgProductionTime": 2,
    "stock": 9
  }
]